_pystmark_meta.py
pystmark.py
pystmark-0.4.6.dist-info/DESCRIPTION.rst
pystmark-0.4.6.dist-info/METADATA
pystmark-0.4.6.dist-info/RECORD
pystmark-0.4.6.dist-info/WHEEL
pystmark-0.4.6.dist-info/metadata.json
pystmark-0.4.6.dist-info/top_level.txt
pystmark-0.4.6.dist-info/version_info.json
