Metadata-Version: 2.0
Name: pystmark
Version: 0.4.6
Summary: A Python library for the Postmark API (http://developer.postmarkapp.com/).
Home-page: https://github.com/xsleonard/pystmark
Author: Steve Leonard
Author-email: sleonard76@gmail.com
License: MIT
Keywords: postmark postmarkapp email
Platform: any
Classifier: Development Status :: 4 - Beta
Classifier: Intended Audience :: Developers
Classifier: Programming Language :: Python
Classifier: Programming Language :: Python :: 2.6
Classifier: Programming Language :: Python :: 2.7
Classifier: Programming Language :: Python :: 3
Classifier: Programming Language :: Python :: 3.2
Classifier: Programming Language :: Python :: 3.3
Classifier: Programming Language :: Python :: Implementation :: PyPy
Classifier: License :: OSI Approved :: MIT License
Classifier: Operating System :: OS Independent
Classifier: Topic :: Internet :: WWW/HTTP
Classifier: Topic :: Software Development :: Libraries :: Python Modules
Classifier: Topic :: Communications :: Email
Requires-Dist: requests (>=1.2.0)
